cloudhub/liblogo.py
cloudhub/livedb.py
cloudhub/lv2.py
cloudhub/maincli.py
cloudhub/candysuite/cloudhub-photolib/photolib.py
cloudhub-0.1.0.post1.dist-info/LICENSE.txt
cloudhub-0.1.0.post1.dist-info/METADATA
cloudhub-0.1.0.post1.dist-info/WHEEL
cloudhub-0.1.0.post1.dist-info/top_level.txt
cloudhub-0.1.0.post1.dist-info/RECORD
