Metadata-Version: 2.1
Name: cloudhub
Version: 0.1.0.post1
Summary: services from sca255
Home-page: https://github.com/arp001-client/cloudhub
Author: sca255
Author-email: arp001dev@outlook.com
Project-URL: Bug Reports, https://github.com/arp001-client/cloudhub/issues
Project-URL: Source, https://github.com/arp001-client/cloudhub/
Keywords: development
Classifier: Development Status :: 5 - Production/Stable
Classifier: Intended Audience :: Developers
Classifier: Topic :: Software Development :: Build Tools
Classifier: License :: OSI Approved :: Mozilla Public License 2.0 (MPL 2.0)
Classifier: Programming Language :: Python :: 3
Classifier: Programming Language :: Python :: 3.7
Classifier: Programming Language :: Python :: 3.8
Classifier: Programming Language :: Python :: 3.9
Classifier: Programming Language :: Python :: 3.10
Classifier: Programming Language :: Python :: 3 :: Only
Requires-Python: >=3.0, <4
License-File: LICENSE.txt
